CHANGELOG.txt
LICENSE.TXT
MANIFEST.in
README.md
setup.py
mjcal/__init__.py
mjcal.egg-info/PKG-INFO
mjcal.egg-info/SOURCES.txt
mjcal.egg-info/dependency_links.txt
mjcal.egg-info/top_level.txt